ExecParser/__init__.py
ExecParser/__main__.py
ExecParser/_version.py
ExecParser/parsers/__init__.py
ExecParser/parsers/abstract.py
ExecParser/parsers/cmdhelper.py
ExecParser/parsers/elf_parser.py
ExecParser/parsers/macho_parser.py
ExecParser/parsers/pe_parser.py
ExecParser-0.1.0.dist-info/LICENSE
ExecParser-0.1.0.dist-info/METADATA
ExecParser-0.1.0.dist-info/WHEEL
ExecParser-0.1.0.dist-info/top_level.txt
ExecParser-0.1.0.dist-info/zip-safe
ExecParser-0.1.0.dist-info/RECORD
